README.md
setup.py
src/vdk/plugin/dag/cached_data_job_executor.py
src/vdk/plugin/dag/dag.py
src/vdk/plugin/dag/dag_plugin.py
src/vdk/plugin/dag/dag_plugin_configuration.py
src/vdk/plugin/dag/dag_runner.py
src/vdk/plugin/dag/dag_validator.py
src/vdk/plugin/dag/dags.py
src/vdk/plugin/dag/exception.py
src/vdk/plugin/dag/local_executor.py
src/vdk/plugin/dag/remote_data_job.py
src/vdk/plugin/dag/remote_data_job_executor.py
src/vdk/plugin/dag/time_based_queue.py
src/vdk/plugin/dag/api/dag.py
src/vdk_dag.egg-info/PKG-INFO
src/vdk_dag.egg-info/SOURCES.txt
src/vdk_dag.egg-info/dependency_links.txt
src/vdk_dag.egg-info/entry_points.txt
src/vdk_dag.egg-info/requires.txt
src/vdk_dag.egg-info/top_level.txt
tests/test_dag.py
tests/test_dag_object.py
tests/test_local_executor.py
tests/test_time_based_queue.py
tests/test_tracking_job_executor.py