Metadata-Version: 2.1
Name: vdk-dag
Version: 0.1.1431637373
Summary: Express dependecies between data jobs.
Home-page: https://github.com/vmware/versatile-data-kit
Classifier: Development Status :: 2 - Pre-Alpha
Classifier: License :: OSI Approved :: Apache Software License
Classifier: Programming Language :: Python :: 3.7
Classifier: Programming Language :: Python :: 3.8
Classifier: Programming Language :: Python :: 3.9
Classifier: Programming Language :: Python :: 3.10
Classifier: Programming Language :: Python :: 3.11
Classifier: Programming Language :: Python :: 3.12
Requires-Dist: vdk-core
Requires-Dist: graphlib-backport
Requires-Dist: vdk-control-api-auth
Requires-Dist: vdk-plugin-control-cli
Requires-Dist: vdk-control-service-api
Requires-Dist: urllib3
